setup.py
lib/ingres_sa_dialect/__init__.py
lib/ingres_sa_dialect/base.py
lib/ingres_sa_dialect/ingresdbi.py
lib/ingres_sa_dialect/zxjdbc.py
lib/ingres_sa_dialect.egg-info/PKG-INFO
lib/ingres_sa_dialect.egg-info/SOURCES.txt
lib/ingres_sa_dialect.egg-info/dependency_links.txt
lib/ingres_sa_dialect.egg-info/entry_points.txt
lib/ingres_sa_dialect.egg-info/top_level.txt