Metadata-Version: 1.0
Name: ingres-sa-dialect
Version: 0.1
Summary: An Ingres dialect for SQLAlchemy
Home-page: UNKNOWN
Author: Anthony Simpson
Author-email: anthony.simpson@ingres.com
License: MIT
Platform: UNKNOWN
